abses/__init__.py
abses/agents/__init__.py
abses/agents/actor.py
abses/agents/container.py
abses/agents/sequences.py
abses/conf/__init__.py
abses/conf/absespy.yaml
abses/conf/default.yaml
abses/core/__init__.py
abses/core/base.py
abses/core/base_module.py
abses/core/base_observable.py
abses/core/base_subsystem.py
abses/core/base_variable.py
abses/core/experiment.py
abses/core/job_manager.py
abses/core/model.py
abses/core/primitives.py
abses/core/protocols.py
abses/core/time_driver.py
abses/core/type_aliases.py
abses/core/types.py
abses/human/__init__.py
abses/human/human.py
abses/human/links.py
abses/space/__init__.py
abses/space/cells.py
abses/space/move.py
abses/space/nature.py
abses/space/patch.py
abses/utils/__init__.py
abses/utils/analysis.py
abses/utils/args.py
abses/utils/config.py
abses/utils/data.py
abses/utils/datacollector.py
abses/utils/errors.py
abses/utils/exp_logging.py
abses/utils/func.py
abses/utils/hydra_logging.py
abses/utils/log_config.py
abses/utils/log_parser.py
abses/utils/logging.py
abses/utils/random.py
abses/utils/regex.py
abses/utils/time.py
abses/utils/tracker/__init__.py
abses/utils/tracker/aim_tracker.py
abses/utils/tracker/default.py
abses/utils/tracker/factory.py
abses/utils/tracker/mlflow_tracker.py
abses/viz/__init__.py
abses/viz/customize_marker.py
abses/viz/plotting.py
abses/viz/solara.py
hydra_plugins/__init__.py
hydra_plugins/abses_searchpath_plugin.py
abses-0.11.5.dist-info/METADATA
abses-0.11.5.dist-info/WHEEL
abses-0.11.5.dist-info/entry_points.txt
abses-0.11.5.dist-info/licenses/LICENSE
abses-0.11.5.dist-info/RECORD
