Metadata-Version: 2.4
Name: abses
Version: 0.11.5
Summary: ABSESpy makes it easier to build artificial Social-ecological systems with real GeoSpatial datasets and fully incorporate human behaviour.
Project-URL: Homepage, https://github.com/SongshGeoLab/ABSESpy
Project-URL: Documentation, https://absespy.github.io/ABSESpy/
Project-URL: Repository, https://github.com/SongshGeoLab/ABSESpy
Author-email: Shuang Song <songshgeo@gmail.com>
License: Apache 2.0 License
License-File: LICENSE
Classifier: Development Status :: 4 - Beta
Classifier: Intended Audience :: Science/Research
Classifier: License :: OSI Approved :: Apache Software License
Classifier: Programming Language :: Python :: 3.11
Classifier: Programming Language :: Python :: 3.12
Classifier: Programming Language :: Python :: 3.13
Requires-Python: <3.14,>=3.11
Requires-Dist: fiona>1.8
Requires-Dist: fontawesome>=5
Requires-Dist: geocube>=0.5.0
Requires-Dist: geopandas<1,>=0
Requires-Dist: hydra-core<1.4,>=1.3
Requires-Dist: icons
Requires-Dist: mesa-geo>=0.9.1
Requires-Dist: mesa>=3.1.0
Requires-Dist: netcdf4>=1.6
Requires-Dist: numpy>=1.26
Requires-Dist: pendulum>=3.0.0
Requires-Dist: rioxarray>=0.13
Requires-Dist: seaborn>=0.13
Requires-Dist: typing-extensions<5,>=4
Requires-Dist: urllib3
Requires-Dist: xarray>=2023
Provides-Extra: aim
Requires-Dist: aim>=3.29.1; extra == 'aim'
Provides-Extra: docs
Requires-Dist: mike>=2.0.0; extra == 'docs'
Requires-Dist: mkdocs-awesome-pages-plugin>=2.9.2; extra == 'docs'
Requires-Dist: mkdocs-bibtex>=2.11.0; extra == 'docs'
Requires-Dist: mkdocs-callouts>=1.9.1; extra == 'docs'
Requires-Dist: mkdocs-exclude>=1.0.2; extra == 'docs'
Requires-Dist: mkdocs-git-authors-plugin>=0.7.2; extra == 'docs'
Requires-Dist: mkdocs-git-revision-date-localized-plugin>=1.2.0; extra == 'docs'
Requires-Dist: mkdocs-glightbox>=0.3.4; extra == 'docs'
Requires-Dist: mkdocs-jupyter>=0.25.1; extra == 'docs'
Requires-Dist: mkdocs-macros-plugin>=1.0.4; extra == 'docs'
Requires-Dist: mkdocs-minify-plugin>=0.7.1; extra == 'docs'
Requires-Dist: mkdocs-redirects>=1.2.1; extra == 'docs'
Requires-Dist: mkdocs-simple-hooks>=0.1.5; extra == 'docs'
Requires-Dist: mkdocs-static-i18n>=1.3.0; extra == 'docs'
Requires-Dist: mkdocs>=1.6.1; extra == 'docs'
Requires-Dist: mkdocstrings>=0.30.1; extra == 'docs'
Requires-Dist: mkdocstrings[python]>=0.24.0; extra == 'docs'
Requires-Dist: nbconvert>=7.16.6; extra == 'docs'
Requires-Dist: nbmake>=1.5.5; extra == 'docs'
Requires-Dist: pymdown-extensions>=10.7; extra == 'docs'
Provides-Extra: mlflow
Requires-Dist: mlflow>=2.3.1; extra == 'mlflow'
